LICENSE.txt
MANIFEST.in
README.md
pyproject.toml
requirements.txt
setup.cfg
setup.py
version.txt
kudu/__init__.pxd
kudu/__init__.py
kudu/client.cpp
kudu/client.pxd
kudu/client.pyx
kudu/compat.py
kudu/config.pxi
kudu/config.pxi.in
kudu/errors.cpp
kudu/errors.pxd
kudu/errors.pyx
kudu/libkudu_client.pxd
kudu/schema.cpp
kudu/schema.pxd
kudu/schema.pyx
kudu/util.py
kudu/version.py
kudu/dummy_tests/dummy_test.py
kudu/tests/__init__.py
kudu/tests/common.py
kudu/tests/test_client.py
kudu/tests/test_scanner.py
kudu/tests/test_scantoken.py
kudu/tests/test_schema.py
kudu/tests/test_util.py
kudu/tests/util.py
kudu_python_cloudera.egg-info/PKG-INFO
kudu_python_cloudera.egg-info/SOURCES.txt
kudu_python_cloudera.egg-info/dependency_links.txt
kudu_python_cloudera.egg-info/requires.txt
kudu_python_cloudera.egg-info/top_level.txt